{
  "metadata": {
    "timestamp": 1736709218832,
    "page": 508,
    "hasNextPage": true,
    "endCursor": "Y3Vyc29yOjUxMA==",
    "completionStatus": "IN_PROGRESS"
  },
  "repositories": [
    {
      "nameWithOwner": "PistonDevelopers/hematite",
      "stars": 1876,
      "defaultBranch": "master",
      "files": [
        {
          "name": ".gitignore",
          "type": "blob",
          "size": 0.2138671875,
          "content": ".DS_Store\n*~\n*#\n*.o\n*.so\n*.swp\n*.dylib\n*.dSYM\n*.dll\n*.rlib\n*.dummy\n*.exe\n*-test\n/assets/minecraft/\n/doc/\n/target/\n/build/\n/.rust/\nrusti.sh\nwatch.sh\n/examples/**\n!/examples/*.rs\n!/examples/assets/\n*.kdev4\n*.trace\n/home/\n"
        },
        {
          "name": ".travis.yml",
          "type": "blob",
          "size": 0.5234375,
          "content": "language: rust\nrust:\n    - nightly\n    - stable\nnotifications:\n    irc: \"irc.mozilla.org#piston-internals\"\nos:\n    - linux\n    - osx\nenv:\n    global:\n        - secure: b65AZCt2SSC/EaI+3T2GS70/Tkym40yf83Ro32Qj5gztKNEVjo/oOJWw6X+HY29V70S4BojhSpnKxv6Z59Uhk/d9ng4lPcjthv5FL1asfhYgIgQa1id3JI1xfkBFAPloLGk/DeSB7G9BZPyVFbfNKimjBf7ViO+odZulq/AGsGI=\nscript:\n    - cargo build -v\n    - cargo test -v\n    - cargo doc -v\nafter_success:\n    - cp -R target/doc doc\n    - curl http://www.rust-ci.org/artifacts/put?t=$RUSTCI_TOKEN | sh\n    - rm -r doc\n"
        },
        {
          "name": "Cargo.dot",
          "type": "blob",
          "size": 1.2919921875,
          "content": "digraph dependencies {\n\tN0[label=\"hematite\"];\n\tN2[label=\"camera_controllers\"];\n\tN3[label=\"docopt\"];\n\tN4[label=\"flate2\"];\n\tN5[label=\"fps_counter\"];\n\tN6[label=\"gfx\"];\n\tN7[label=\"gfx_device_gl\"];\n\tN10[label=\"piston\"];\n\tN11[label=\"piston3d-gfx_voxel\"];\n\tN12[label=\"pistoncore-glutin_window\"];\n\tN15[label=\"time\"];\n\tN16[label=\"vecmath\"];\n\tN26[label=\"piston3d-cam\"];\n\tN27[label=\"pistoncore-input\"];\n\tN89[label=\"pistoncore-event_loop\"];\n\tN90[label=\"pistoncore-window\"];\n\tN91[label=\"piston-float\"];\n\tN92[label=\"piston-gfx_texture\"];\n\tN93[label=\"piston-texture\"];\n\tN94[label=\"piston-viewport\"];\n\tN0 -> N2[label=\"\"];\n\tN0 -> N3[label=\"\"];\n\tN0 -> N4[label=\"\"];\n\tN0 -> N5[label=\"\"];\n\tN0 -> N6[label=\"\"];\n\tN0 -> N7[label=\"\"];\n\tN0 -> N10[label=\"\"];\n\tN0 -> N11[label=\"\"];\n\tN0 -> N12[label=\"\"];\n\tN0 -> N15[label=\"\"];\n\tN0 -> N16[label=\"\"];\n\tN2 -> N16[label=\"\"];\n\tN2 -> N26[label=\"\"];\n\tN2 -> N27[label=\"\"];\n\tN5 -> N15[label=\"\"];\n\tN10 -> N27[label=\"\"];\n\tN10 -> N89[label=\"\"];\n\tN10 -> N90[label=\"\"];\n\tN11 -> N6[label=\"\"];\n\tN11 -> N92[label=\"\"];\n\tN12 -> N27[label=\"\"];\n\tN12 -> N90[label=\"\"];\n\tN16 -> N91[label=\"\"];\n\tN26 -> N16[label=\"\"];\n\tN27 -> N94[label=\"\"];\n\tN89 -> N15[label=\"\"];\n\tN89 -> N27[label=\"\"];\n\tN89 -> N90[label=\"\"];\n\tN89 -> N94[label=\"\"];\n\tN90 -> N27[label=\"\"];\n\tN92 -> N6[label=\"\"];\n\tN92 -> N93[label=\"\"];\n\tN94 -> N91[label=\"\"];\n}\n"
        },
        {
          "name": "Cargo.lock",
          "type": "blob",
          "size": 49.234375,
          "content": "# This file is automatically @generated by Cargo.\n# It is not intended for manual editing.\nversion = 3\n\n[[package]]\nname = \"ab_glyph_rasterizer\"\nversion = \"0.1.7\"\nsource = \"registry+https://github.com/rust-lang/crates.io-index\"\nchecksum = \"330223a1aecc308757b9926e9391c9b47f8ef2dbd8aea9df88312aea18c5e8d6\"\n\n[[package]]\nname = \"adler\"\nversion = \"1.0.2\"\nsource = \"registry+https://github.com/rust-lang/crates.io-index\"\nchecksum = \"f26201604c87b1e01bd3d98f8d5d9a8fcbb815e8cedb41ffccbeb4bf593a35fe\"\n\n[[package]]\nname = \"adler32\"\nversion = \"1.2.0\"\nsource = \"registry+https://github.com/rust-lang/crates.io-index\"\nchecksum = \"aae1277d39aeec15cb388266ecc24b11c80469deae6067e17a1a7aa9e5c1f234\"\n\n[[package]]\nname = \"aho-corasick\"\nversion = \"0.6.10\"\nsource = \"registry+https://github.com/rust-lang/crates.io-index\"\nchecksum = \"81ce3d38065e618af2d7b77e10c5ad9a069859b4be3c2250f674af3840d9c8a5\"\ndependencies = [\n \"memchr\",\n]\n\n[[package]]\nname = \"andrew\"\nversion = \"0.3.1\"\nsource = \"registry+https://github.com/rust-lang/crates.io-index\"\nchecksum = \"8c4afb09dd642feec8408e33f92f3ffc4052946f6b20f32fb99c1f58cd4fa7cf\"\ndependencies = [\n \"bitflags\",\n \"rusttype\",\n \"walkdir\",\n \"xdg\",\n \"xml-rs 0.8.3\",\n]\n\n[[package]]\nname = \"android_glue\"\nversion = \"0.2.3\"\nsource = \"registry+https://github.com/rust-lang/crates.io-index\"\nchecksum = \"000444226fcff248f2bc4c7625be32c63caccfecc2723a2b9f78a7487a49c407\"\n\n[[package]]\nname = \"array\"\nversion = \"0.0.1\"\nsource = \"registry+https://github.com/rust-lang/crates.io-index\"\nchecksum = \"bf27051ee75000297d5afad639a434ad6d3d7d3136ccaab75a1b7c439b9afa11\"\n\n[[package]]\nname = \"autocfg\"\nversion = \"1.0.1\"\nsource = \"registry+https://github.com/rust-lang/crates.io-index\"\nchecksum = \"cdb031dd78e28731d87d56cc8ffef4a8f36ca26c38fe2de700543e627f8a464a\"\n\n[[package]]\nname = \"bitflags\"\nversion = \"1.2.1\"\nsource = \"registry+https://github.com/rust-lang/crates.io-index\"\nchecksum = \"cf1de2fe8c75bc145a2f577add951f8134889b4795d47466a54a5c846d691693\"\n\n[[package]]\nname = \"block\"\nversion = \"0.1.6\"\nsource = \"registry+https://github.com/rust-lang/crates.io-index\"\nchecksum = \"0d8c1fef690941d3e7788d328517591fecc684c084084702d6ff1641e993699a\"\n\n[[package]]\nname = \"byteorder\"\nversion = \"1.4.3\"\nsource = \"registry+https://github.com/rust-lang/crates.io-index\"\nchecksum = \"14c189c53d098945499cdfa7ecc63567cf3886b3332b312a5b4585d8d3a6a610\"\n\n[[package]]\nname = \"bzip2\"\nversion = \"0.4.4\"\nsource = \"registry+https://github.com/rust-lang/crates.io-index\"\nchecksum = \"bdb116a6ef3f6c3698828873ad02c3014b3c85cadb88496095628e3ef1e347f8\"\ndependencies = [\n \"bzip2-sys\",\n \"libc\",\n]\n\n[[package]]\nname = \"bzip2-sys\"\nversion = \"0.1.11+1.0.8\"\nsource = \"registry+https://github.com/rust-lang/crates.io-index\"\nchecksum = \"736a955f3fa7875102d57c82b8cac37ec45224a07fd32d58f9f7a186b6cd4cdc\"\ndependencies = [\n \"cc\",\n \"libc\",\n \"pkg-config\",\n]\n\n[[package]]\nname = \"calloop\"\nversion = \"0.6.5\"\nsource = \"registry+https://github.com/rust-lang/crates.io-index\"\nchecksum = \"0b036167e76041694579972c28cf4877b4f92da222560ddb49008937b6a6727c\"\ndependencies = [\n \"log\",\n \"nix 0.18.0\",\n]\n\n[[package]]\nname = \"camera_controllers\"\nversion = \"0.32.0\"\nsource = \"registry+https://github.com/rust-lang/crates.io-index\"\nchecksum = \"832c5e36b91a2cd7d29f4fe76b1464b1288326f450bc829cf75b62fc4a1fed26\"\ndependencies = [\n \"bitflags\",\n \"piston3d-cam\",\n \"pistoncore-input\",\n \"quaternion\",\n \"vecmath\",\n]\n\n[[package]]\nname = \"cc\"\nversion = \"1.0.69\"\nsource = \"registry+https://github.com/rust-lang/crates.io-index\"\nchecksum = \"e70cc2f62c6ce1868963827bd677764c62d07c3d9a3e1fb1177ee1a9ab199eb2\"\n\n[[package]]\nname = \"cfg-if\"\nversion = \"0.1.10\"\nsource = \"registry+https://github.com/rust-lang/crates.io-index\"\nchecksum = \"4785bdd1c96b2a846b2bd7cc02e86b6b3dbf14e7e53446c4f54c92a361040822\"\n\n[[package]]\nname = \"cfg-if\"\nversion = \"1.0.0\"\nsource = \"registry+https://github.com/rust-lang/crates.io-index\"\nchecksum = \"baf1de4339761588bc0619e3cbc0120ee582ebb74b53b4efbf79117bd2da40fd\"\n\n[[package]]\nname = \"cgl\"\nversion = \"0.3.2\"\nsource = \"registry+https://github.com/rust-lang/crates.io-index\"\nchecksum = \"0ced0551234e87afee12411d535648dd89d2e7f34c78b753395567aff3d447ff\"\ndependencies = [\n \"libc\",\n]\n\n[[package]]\nname = \"cocoa\"\nversion = \"0.23.0\"\nsource = \"registry+https://github.com/rust-lang/crates.io-index\"\nchecksum = \"c54201c07dcf3a5ca33fececb8042aed767ee4bfd5a0235a8ceabcda956044b2\"\ndependencies = [\n \"bitflags\",\n \"block\",\n \"cocoa-foundation\",\n \"core-foundation 0.9.3\",\n \"core-graphics 0.22.3\",\n \"foreign-types\",\n \"libc\",\n \"objc\",\n]\n\n[[package]]\nname = \"cocoa\"\nversion = \"0.24.1\"\nsource = \"registry+https://github.com/rust-lang/crates.io-index\"\nchecksum = \"f425db7937052c684daec3bd6375c8abe2d146dca4b8b143d6db777c39138f3a\"\ndependencies = [\n \"bitflags\",\n \"block\",\n \"cocoa-foundation\",\n \"core-foundation 0.9.3\",\n \"core-graphics 0.22.3\",\n \"foreign-types\",\n \"libc\",\n \"objc\",\n]\n\n[[package]]\nname = \"cocoa-foundation\"\nversion = \"0.1.0\"\nsource = \"registry+https://github.com/rust-lang/crates.io-index\"\nchecksum = \"7ade49b65d560ca58c403a479bb396592b155c0185eada742ee323d1d68d6318\"\ndependencies = [\n \"bitflags\",\n \"block\",\n \"core-foundation 0.9.3\",\n \"core-graphics-types\",\n \"foreign-types\",\n \"libc\",\n \"objc\",\n]\n\n[[package]]\nname = \"color_quant\"\nversion = \"1.1.0\"\nsource = \"registry+https://github.com/rust-lang/crates.io-index\"\nchecksum = \"3d7b894f5411737b7867f4827955924d7c254fc9f4d91a6aad6b097804b1018b\"\n\n[[package]]\nname = \"core-foundation\"\nversion = \"0.7.0\"\nsource = \"registry+https://github.com/rust-lang/crates.io-index\"\nchecksum = \"57d24c7a13c43e870e37c1556b74555437870a04514f7685f5b354e090567171\"\ndependencies = [\n \"core-foundation-sys 0.7.0\",\n \"libc\",\n]\n\n[[package]]\nname = \"core-foundation\"\nversion = \"0.9.3\"\nsource = \"registry+https://github.com/rust-lang/crates.io-index\"\nchecksum = \"194a7a9e6de53fa55116934067c844d9d749312f75c6f6d0980e8c252f8c2146\"\ndependencies = [\n \"core-foundation-sys 0.8.3\",\n \"libc\",\n]\n\n[[package]]\nname = \"core-foundation-sys\"\nversion = \"0.7.0\"\nsource = \"registry+https://github.com/rust-lang/crates.io-index\"\nchecksum = \"b3a71ab494c0b5b860bdc8407ae08978052417070c2ced38573a9157ad75b8ac\"\n\n[[package]]\nname = \"core-foundation-sys\"\nversion = \"0.8.3\"\nsource = \"registry+https://github.com/rust-lang/crates.io-index\"\nchecksum = \"5827cebf4670468b8772dd191856768aedcb1b0278a04f989f7766351917b9dc\"\n\n[[package]]\nname = \"core-graphics\"\nversion = \"0.19.2\"\nsource = \"registry+https://github.com/rust-lang/crates.io-index\"\nchecksum = \"b3889374e6ea6ab25dba90bb5d96202f61108058361f6dc72e8b03e6f8bbe923\"\ndependencies = [\n \"bitflags\",\n \"core-foundation 0.7.0\",\n \"foreign-types\",\n \"libc\",\n]\n\n[[package]]\nname = \"core-graphics\"\nversion = \"0.22.3\"\nsource = \"registry+https://github.com/rust-lang/crates.io-index\"\nchecksum = \"2581bbab3b8ffc6fcbd550bf46c355135d16e9ff2a6ea032ad6b9bf1d7efe4fb\"\ndependencies = [\n \"bitflags\",\n \"core-foundation 0.9.3\",\n \"core-graphics-types\",\n \"foreign-types\",\n \"libc\",\n]\n\n[[package]]\nname = \"core-graphics-types\"\nversion = \"0.1.1\"\nsource = \"registry+https://github.com/rust-lang/crates.io-index\"\nchecksum = \"3a68b68b3446082644c91ac778bf50cd4104bfb002b5a6a7c44cca5a2c70788b\"\ndependencies = [\n \"bitflags\",\n \"core-foundation 0.9.3\",\n \"foreign-types\",\n \"libc\",\n]\n\n[[package]]\nname = \"core-video-sys\"\nversion = \"0.1.4\"\nsource = \"registry+https://github.com/rust-lang/crates.io-index\"\nchecksum = \"34ecad23610ad9757664d644e369246edde1803fcb43ed72876565098a5d3828\"\ndependencies = [\n \"cfg-if 0.1.10\",\n \"core-foundation-sys 0.7.0\",\n \"core-graphics 0.19.2\",\n \"libc\",\n \"objc\",\n]\n\n[[package]]\nname = \"crc32fast\"\nversion = \"1.2.1\"\nsource = \"registry+https://github.com/rust-lang/crates.io-index\"\nchecksum = \"81156fece84ab6a9f2afdb109ce3ae577e42b1228441eded99bd77f627953b1a\"\ndependencies = [\n \"cfg-if 1.0.0\",\n]\n\n[[package]]\nname = \"crossbeam-channel\"\nversion = \"0.5.1\"\nsource = \"registry+https://github.com/rust-lang/crates.io-index\"\nchecksum = \"06ed27e177f16d65f0f0c22a213e17c696ace5dd64b14258b52f9417ccb52db4\"\ndependencies = [\n \"cfg-if 1.0.0\",\n \"crossbeam-utils\",\n]\n\n[[package]]\nname = \"crossbeam-deque\"\nversion = \"0.8.1\"\nsource = \"registry+https://github.com/rust-lang/crates.io-index\"\nchecksum = \"6455c0ca19f0d2fbf751b908d5c55c1f5cbc65e03c4225427254b46890bdde1e\"\ndependencies = [\n \"cfg-if 1.0.0\",\n \"crossbeam-epoch\",\n \"crossbeam-utils\",\n]\n\n[[package]]\nname = \"crossbeam-epoch\"\nversion = \"0.9.5\"\nsource = \"registry+https://github.com/rust-lang/crates.io-index\"\nchecksum = \"4ec02e091aa634e2c3ada4a392989e7c3116673ef0ac5b72232439094d73b7fd\"\ndependencies = [\n \"cfg-if 1.0.0\",\n \"crossbeam-utils\",\n \"lazy_static 1.4.0\",\n \"memoffset\",\n \"scopeguard\",\n]\n\n[[package]]\nname = \"crossbeam-utils\"\nversion = \"0.8.8\"\nsource = \"registry+https://github.com/rust-lang/crates.io-index\"\nchecksum = \"0bf124c720b7686e3c2663cf54062ab0f68a88af2fb6a030e87e30bf721fcb38\"\ndependencies = [\n \"cfg-if 1.0.0\",\n \"lazy_static 1.4.0\",\n]\n\n[[package]]\nname = \"cty\"\nversion = \"0.2.2\"\nsource = \"registry+https://github.com/rust-lang/crates.io-index\"\nchecksum = \"b365fabc795046672053e29c954733ec3b05e4be654ab130fe8f1f94d7051f35\"\n\n[[package]]\nname = \"darling\"\nversion = \"0.10.2\"\nsource = \"registry+https://github.com/rust-lang/crates.io-index\"\nchecksum = \"0d706e75d87e35569db781a9b5e2416cff1236a47ed380831f959382ccd5f858\"\ndependencies = [\n \"darling_core\",\n \"darling_macro\",\n]\n\n[[package]]\nname = \"darling_core\"\nversion = \"0.10.2\"\nsource = \"registry+https://github.com/rust-lang/crates.io-index\"\nchecksum = \"f0c960ae2da4de88a91b2d920c2a7233b400bc33cb28453a2987822d8392519b\"\ndependencies = [\n \"fnv\",\n \"ident_case\",\n \"proc-macro2 1.0.27\",\n \"quote 1.0.9\",\n \"strsim 0.9.3\",\n \"syn 1.0.73\",\n]\n\n[[package]]\nname = \"darling_macro\"\nversion = \"0.10.2\"\nsource = \"registry+https://github.com/rust-lang/crates.io-index\"\nchecksum = \"d9b5a2f4ac4969822c62224815d069952656cadc7084fdca9751e6d959189b72\"\ndependencies = [\n \"darling_core\",\n \"quote 1.0.9\",\n \"syn 1.0.73\",\n]\n\n[[package]]\nname = \"deflate\"\nversion = \"0.7.20\"\nsource = \"registry+https://github.com/rust-lang/crates.io-index\"\nchecksum = \"707b6a7b384888a70c8d2e8650b3e60170dfc6a67bb4aa67b6dfca57af4bedb4\"\ndependencies = [\n \"adler32\",\n \"byteorder\",\n]\n\n[[package]]\nname = \"derivative\"\nversion = \"1.0.4\"\nsource = \"registry+https://github.com/rust-lang/crates.io-index\"\nchecksum = \"3c6d883546668a3e2011b6a716a7330b82eabb0151b138217f632c8243e17135\"\ndependencies = [\n \"proc-macro2 0.4.30\",\n \"quote 0.6.13\",\n \"syn 0.15.44\",\n]\n\n[[package]]\nname = \"derivative\"\nversion = \"2.2.0\"\nsource = \"registry+https://github.com/rust-lang/crates.io-index\"\nchecksum = \"fcc3dd5e9e9c0b295d6e1e4d811fb6f157d5ffd784b8d202fc62eac8035a770b\"\ndependencies = [\n \"proc-macro2 1.0.27\",\n \"quote 1.0.9\",\n \"syn 1.0.73\",\n]\n\n[[package]]\nname = \"dispatch\"\nversion = \"0.2.0\"\nsource = \"registry+https://github.com/rust-lang/crates.io-index\"\nchecksum = \"bd0c93bb4b0c6d9b77f4435b0ae98c24d17f1c45b2ff844c6151a07256ca923b\"\n\n[[package]]\nname = \"dlib\"\nversion = \"0.4.2\"\nsource = \"registry+https://github.com/rust-lang/crates.io-index\"\nchecksum = \"b11f15d1e3268f140f68d390637d5e76d849782d971ae7063e0da69fe9709a76\"\ndependencies = [\n \"libloading 0.6.7\",\n]\n\n[[package]]\nname = \"dlib\"\nversion = \"0.5.0\"\nsource = \"registry+https://github.com/rust-lang/crates.io-index\"\nchecksum = \"ac1b7517328c04c2aa68422fc60a41b92208182142ed04a25879c26c8f878794\"\ndependencies = [\n \"libloading 0.7.4\",\n]\n\n[[package]]\nname = \"docopt\"\nversion = \"0.7.0\"\nsource = \"registry+https://github.com/rust-lang/crates.io-index\"\nchecksum = \"ab32ea6e284d87987066f21a9e809a73c14720571ef34516f0890b3d355ccfd8\"\ndependencies = [\n \"lazy_static 0.2.11\",\n \"regex\",\n \"rustc-serialize\",\n \"strsim 0.6.0\",\n]\n\n[[package]]\nname = \"downcast-rs\"\nversion = \"1.2.0\"\nsource = \"registry+https://github.com/rust-lang/crates.io-index\"\nchecksum = \"9ea835d29036a4087793836fa931b08837ad5e957da9e23886b29586fb9b6650\"\n\n[[package]]\nname = \"draw_state\"\nversion = \"0.8.0\"\nsource = \"registry+https://github.com/rust-lang/crates.io-index\"\nchecksum = \"33cf9537e2d06891448799b96d5a8c8083e0e90522a7fdabe6ebf4f41d79d651\"\ndependencies = [\n \"bitflags\",\n]\n\n[[package]]\nname = \"either\"\nversion = \"1.6.1\"\nsource = \"registry+https://github.com/rust-lang/crates.io-index\"\nchecksum = \"e78d4f1cc4ae33bbfc157ed5d5a5ef3bc29227303d595861deb238fcec4e9457\"\n\n[[package]]\nname = \"flate2\"\nversion = \"1.0.20\"\nsource = \"registry+https://github.com/rust-lang/crates.io-index\"\nchecksum = \"cd3aec53de10fe96d7d8c565eb17f2c687bb5518a2ec453b5b1252964526abe0\"\ndependencies = [\n \"cfg-if 1.0.0\",\n \"crc32fast\",\n \"libc\",\n \"miniz_oxide\",\n]\n\n[[package]]\nname = \"fnv\"\nversion = \"1.0.7\"\nsource = \"registry+https://github.com/rust-lang/crates.io-index\"\nchecksum = \"3f9eec918d3f24069decb9af1554cad7c880e2da24a9afd88aca000531ab82c1\"\n\n[[package]]\nname = \"foreign-types\"\nversion = \"0.3.2\"\nsource = \"registry+https://github.com/rust-lang/crates.io-index\"\nchecksum = \"f6f339eb8adc052cd2ca78910fda869aefa38d22d5cb648e6485e4d3fc06f3b1\"\ndependencies = [\n \"foreign-types-shared\",\n]\n\n[[package]]\nname = \"foreign-types-shared\"\nversion = \"0.1.1\"\nsource = \"registry+https://github.com/rust-lang/crates.io-index\"\nchecksum = \"00b0228411908ca8685dba7fc2cdd70ec9990a6e753e89b6ac91a84c40fbaf4b\"\n\n[[package]]\nname = \"fps_counter\"\nversion = \"2.0.0\"\nsource = \"registry+https://github.com/rust-lang/crates.io-index\"\nchecksum = \"3aaba7ff514ee9d802b562927f80b1e94e93d8e74c31b134c9c3762dabf1a36b\"\n\n[[package]]\nname = \"fs2\"\nversion = \"0.4.3\"\nsource = \"registry+https://github.com/rust-lang/crates.io-index\"\nchecksum = \"9564fc758e15025b46aa6643b1b77d047d1a56a1aea6e01002ac0c7026876213\"\ndependencies = [\n \"libc\",\n \"winapi 0.3.9\",\n]\n\n[[package]]\nname = \"fuchsia-zircon\"\nversion = \"0.3.3\"\nsource = \"registry+https://github.com/rust-lang/crates.io-index\"\nchecksum = \"2e9763c69ebaae630ba35f74888db465e49e259ba1bc0eda7d06f4a067615d82\"\ndependencies = [\n \"bitflags\",\n \"fuchsia-zircon-sys\",\n]\n\n[[package]]\nname = \"fuchsia-zircon-sys\"\nversion = \"0.3.3\"\nsource = \"registry+https://github.com/rust-lang/crates.io-index\"\nchecksum = \"3dcaa9ae7725d12cdb85b3ad99a434db70b468c09ded17e012d86b5c1010f7a7\"\n\n[[package]]\nname = \"gfx\"\nversion = \"0.17.1\"\nsource = \"registry+https://github.com/rust-lang/crates.io-index\"\nchecksum = \"7d7ce0c1f747245342a73453fdb098ea0764c430421fbc4d98cdc8ef8ede4834\"\ndependencies = [\n \"derivative 1.0.4\",\n \"draw_state\",\n \"gfx_core\",\n \"log\",\n]\n\n[[package]]\nname = \"gfx_core\"\nversion = \"0.8.3\"\nsource = \"registry+https://github.com/rust-lang/crates.io-index\"\nchecksum = \"c74932837e61f20956c3da1a47471513707dde300274812bba94373ab51830ae\"\ndependencies = [\n \"bitflags\",\n \"derivative 1.0.4\",\n \"draw_state\",\n \"log\",\n]\n\n[[package]]\nname = \"gfx_device_gl\"\nversion = \"0.15.5\"\nsource = \"registry+https://github.com/rust-lang/crates.io-index\"\nchecksum = \"def9cc76ab9ae3187a1ef5edb16c263fa7d713319ffa1d46e00c9d348081a982\"\ndependencies = [\n \"gfx_core\",\n \"gfx_gl\",\n \"log\",\n]\n\n[[package]]\nname = \"gfx_gl\"\nversion = \"0.5.0\"\nsource = \"registry+https://github.com/rust-lang/crates.io-index\"\nchecksum = \"3e8a920f8f6c1025a7ddf9dd25502bf059506fd3cd765dfbe8dba0b56b7eeecb\"\ndependencies = [\n \"gl_generator 0.9.0\",\n]\n\n[[package]]\nname = \"gif\"\nversion = \"0.10.3\"\nsource = \"registry+https://github.com/rust-lang/crates.io-index\"\nchecksum = \"471d90201b3b223f3451cd4ad53e34295f16a1df17b1edf3736d47761c3981af\"\ndependencies = [\n \"color_quant\",\n \"lzw\",\n]\n\n[[package]]\nname = \"gl\"\nversion = \"0.13.0\"\nsource = \"registry+https://github.com/rust-lang/crates.io-index\"\nchecksum = \"4b411c7e0bfc599e3606412c190e786b5bb48cf00073e1635f9bb6f88fe7d84a\"\ndependencies = [\n \"gl_generator 0.13.1\",\n]\n\n[[package]]\nname = \"gl_generator\"\nversion = \"0.9.0\"\nsource = \"registry+https://github.com/rust-lang/crates.io-index\"\nchecksum = \"7a795170cbd85b5a7baa58d6d7525cae6a03e486859860c220f7ebbbdd379d0a\"\ndependencies = [\n \"khronos_api 2.2.0\",\n \"log\",\n \"xml-rs 0.7.0\",\n]\n\n[[package]]\nname = \"gl_generator\"\nversion = \"0.13.1\"\nsource = \"registry+https://github.com/rust-lang/crates.io-index\"\nchecksum = \"ca98bbde17256e02d17336a6bdb5a50f7d0ccacee502e191d3e3d0ec2f96f84a\"\ndependencies = [\n \"khronos_api 3.1.0\",\n \"log\",\n \"xml-rs 0.8.3\",\n]\n\n[[package]]\nname = \"gl_generator\"\nversion = \"0.14.0\"\nsource = \"registry+https://github.com/rust-lang/crates.io-index\"\nchecksum = \"1a95dfc23a2b4a9a2f5ab41d194f8bfda3cabec42af4e39f08c339eb2a0c124d\"\ndependencies = [\n \"khronos_api 3.1.0\",\n \"log\",\n \"xml-rs 0.8.3\",\n]\n\n[[package]]\nname = \"glutin\"\nversion = \"0.26.0\"\nsource = \"registry+https://github.com/rust-lang/crates.io-index\"\nchecksum = \"1ae1cbb9176b9151c4ce03f012e3cd1c6c18c4be79edeaeb3d99f5d8085c5fa3\"\ndependencies = [\n \"android_glue\",\n \"cgl\",\n \"cocoa 0.23.0\",\n \"core-foundation 0.9.3\",\n \"glutin_egl_sys\",\n \"glutin_emscripten_sys\",\n \"glutin_gles2_sys\",\n \"glutin_glx_sys\",\n \"glutin_wgl_sys\",\n \"lazy_static 1.4.0\",\n \"libloading 0.6.7\",\n \"log\",\n \"objc\",\n \"osmesa-sys\",\n \"parking_lot\",\n \"wayland-client\",\n \"wayland-egl\",\n \"winapi 0.3.9\",\n \"winit\",\n]\n\n[[package]]\nname = \"glutin_egl_sys\"\nversion = \"0.1.6\"\nsource = \"registry+https://github.com/rust-lang/crates.io-index\"\nchecksum = \"68900f84b471f31ea1d1355567eb865a2cf446294f06cef8d653ed7bcf5f013d\"\ndependencies = [\n \"gl_generator 0.14.0\",\n \"winapi 0.3.9\",\n]\n\n[[package]]\nname = \"glutin_emscripten_sys\"\nversion = \"0.1.1\"\nsource = \"registry+https://github.com/rust-lang/crates.io-index\"\nchecksum = \"80de4146df76e8a6c32b03007bc764ff3249dcaeb4f675d68a06caf1bac363f1\"\n\n[[package]]\nname = \"glutin_gles2_sys\"\nversion = \"0.1.5\"\nsource = \"registry+https://github.com/rust-lang/crates.io-index\"\nchecksum = \"e8094e708b730a7c8a1954f4f8a31880af00eb8a1c5b5bf85d28a0a3c6d69103\"\ndependencies = [\n \"gl_generator 0.14.0\",\n \"objc\",\n]\n\n[[package]]\nname = \"glutin_glx_sys\"\nversion = \"0.1.8\"\nsource = \"registry+https://github.com/rust-lang/crates.io-index\"\nchecksum = \"d93d0575865098580c5b3a423188cd959419912ea60b1e48e8b3b526f6d02468\"\ndependencies = [\n \"gl_generator 0.14.0\",\n \"x11-dl\",\n]\n\n[[package]]\nname = \"glutin_wgl_sys\"\nversion = \"0.1.5\"\nsource = \"registry+https://github.com/rust-lang/crates.io-index\"\nchecksum = \"3da5951a1569dbab865c6f2a863efafff193a93caf05538d193e9e3816d21696\"\ndependencies = [\n \"gl_generator 0.14.0\",\n]\n\n[[package]]\nname = \"hematite\"\nversion = \"0.0.34\"\ndependencies = [\n \"byteorder\",\n \"camera_controllers\",\n \"docopt\",\n \"flate2\",\n \"fps_counter\",\n \"gfx\",\n \"gfx_core\",\n \"gfx_device_gl\",\n \"libc\",\n \"memmap\",\n \"piston\",\n \"piston3d-gfx_voxel\",\n \"pistoncore-glutin_window\",\n \"rustc-serialize\",\n \"shader_version\",\n \"vecmath\",\n \"zip\",\n]\n\n[[package]]\nname = \"hermit-abi\"\nversion = \"0.1.19\"\nsource = \"registry+https://github.com/rust-lang/crates.io-index\"\nchecksum = \"62b467343b94ba476dcb2500d242dadbb39557df889310ac77c5d99100aaac33\"\ndependencies = [\n \"libc\",\n]\n\n[[package]]\nname = \"ident_case\"\nversion = \"1.0.1\"\nsource = \"registry+https://github.com/rust-lang/crates.io-index\"\nchecksum = \"b9e0384b61958566e926dc50660321d12159025e767c18e043daf26b70104c39\"\n\n[[package]]\nname = \"image\"\nversion = \"0.21.3\"\nsource = \"registry+https://github.com/rust-lang/crates.io-index\"\nchecksum = \"35371e467cd7b0b3d1d6013d619203658467df12d61b0ca43cd67b743b1965eb\"\ndependencies = [\n \"byteorder\",\n \"gif\",\n \"jpeg-decoder\",\n \"lzw\",\n \"num-iter\",\n \"num-rational\",\n \"num-traits\",\n \"png\",\n \"scoped_threadpool\",\n \"tiff\",\n]\n\n[[package]]\nname = \"inflate\"\nversion = \"0.4.5\"\nsource = \"registry+https://github.com/rust-lang/crates.io-index\"\nchecksum = \"1cdb29978cc5797bd8dcc8e5bf7de604891df2a8dc576973d71a281e916db2ff\"\ndependencies = [\n \"adler32\",\n]\n\n[[package]]\nname = \"instant\"\nversion = \"0.1.12\"\nsource = \"registry+https://github.com/rust-lang/crates.io-index\"\nchecksum = \"7a5bbe824c507c5da5956355e86a746d82e0e1464f65d862cc5e71da70e94b2c\"\ndependencies = [\n \"cfg-if 1.0.0\",\n]\n\n[[package]]\nname = \"iovec\"\nversion = \"0.1.4\"\nsource = \"registry+https://github.com/rust-lang/crates.io-index\"\nchecksum = \"b2b3ea6ff95e175473f8ffe6a7eb7c00d054240321b84c57051175fe3c1e075e\"\ndependencies = [\n \"libc\",\n]\n\n[[package]]\nname = \"jni-sys\"\nversion = \"0.3.0\"\nsource = \"registry+https://github.com/rust-lang/crates.io-index\"\nchecksum = \"8eaf4bc02d17cbdd7ff4c7438cafcdf7fb9a4613313ad11b4f8fefe7d3fa0130\"\n\n[[package]]\nname = \"jpeg-decoder\"\nversion = \"0.1.22\"\nsource = \"registry+https://github.com/rust-lang/crates.io-index\"\nchecksum = \"229d53d58899083193af11e15917b5640cd40b29ff475a1fe4ef725deb02d0f2\"\ndependencies = [\n \"rayon\",\n]\n\n[[package]]\nname = \"kernel32-sys\"\nversion = \"0.2.2\"\nsource = \"registry+https://github.com/rust-lang/crates.io-index\"\nchecksum = \"7507624b29483431c0ba2d82aece8ca6cdba9382bff4ddd0f7490560c056098d\"\ndependencies = [\n \"winapi 0.2.8\",\n \"winapi-build\",\n]\n\n[[package]]\nname = \"khronos_api\"\nversion = \"2.2.0\"\nsource = \"registry+https://github.com/rust-lang/crates.io-index\"\nchecksum = \"037ab472c33f67b5fbd3e9163a2645319e5356fcd355efa6d4eb7fff4bbcb554\"\n\n[[package]]\nname = \"khronos_api\"\nversion = \"3.1.0\"\nsource = \"registry+https://github.com/rust-lang/crates.io-index\"\nchecksum = \"e2db585e1d738fc771bf08a151420d3ed193d9d895a36df7f6f8a9456b911ddc\"\n\n[[package]]\nname = \"lazy_static\"\nversion = \"0.2.11\"\nsource = \"registry+https://github.com/rust-lang/crates.io-index\"\nchecksum = \"76f033c7ad61445c5b347c7382dd1237847eb1bce590fe50365dcb33d546be73\"\n\n[[package]]\nname = \"lazy_static\"\nversion = \"1.4.0\"\nsource = \"registry+https://github.com/rust-lang/crates.io-index\"\nchecksum = \"e2abad23fbc42b3700f2f279844dc832adb2b2eb069b2df918f455c4e18cc646\"\n\n[[package]]\nname = \"lazycell\"\nversion = \"1.3.0\"\nsource = \"registry+https://github.com/rust-lang/crates.io-index\"\nchecksum = \"830d08ce1d1d941e6b30645f1a0eb5643013d835ce3779a5fc208261dbe10f55\"\n\n[[package]]\nname = \"libc\"\nversion = \"0.2.137\"\nsource = \"registry+https://github.com/rust-lang/crates.io-index\"\nchecksum = \"fc7fcc620a3bff7cdd7a365be3376c97191aeaccc2a603e600951e452615bf89\"\n\n[[package]]\nname = \"libloading\"\nversion = \"0.6.7\"\nsource = \"registry+https://github.com/rust-lang/crates.io-index\"\nchecksum = \"351a32417a12d5f7e82c368a66781e307834dae04c6ce0cd4456d52989229883\"\ndependencies = [\n \"cfg-if 1.0.0\",\n \"winapi 0.3.9\",\n]\n\n[[package]]\nname = \"libloading\"\nversion = \"0.7.4\"\nsource = \"registry+https://github.com/rust-lang/crates.io-index\"\nchecksum = \"b67380fd3b2fbe7527a606e18729d21c6f3951633d0500574c4dc22d2d638b9f\"\ndependencies = [\n \"cfg-if 1.0.0\",\n \"winapi 0.3.9\",\n]\n\n[[package]]\nname = \"lock_api\"\nversion = \"0.4.6\"\nsource = \"registry+https://github.com/rust-lang/crates.io-index\"\nchecksum = \"88943dd7ef4a2e5a4bfa2753aaab3013e34ce2533d1996fb18ef591e315e2b3b\"\ndependencies = [\n \"scopeguard\",\n]\n\n[[package]]\nname = \"log\"\nversion = \"0.4.14\"\nsource = \"registry+https://github.com/rust-lang/crates.io-index\"\nchecksum = \"51b9bbe6c47d51fc3e1a9b945965946b4c44142ab8792c50835a980d362c2710\"\ndependencies = [\n \"cfg-if 1.0.0\",\n]\n\n[[package]]\nname = \"lzw\"\nversion = \"0.10.0\"\nsource = \"registry+https://github.com/rust-lang/crates.io-index\"\nchecksum = \"7d947cbb889ed21c2a84be6ffbaebf5b4e0f4340638cba0444907e38b56be084\"\n\n[[package]]\nname = \"malloc_buf\"\nversion = \"0.0.6\"\nsource = \"registry+https://github.com/rust-lang/crates.io-index\"\nchecksum = \"62bb907fe88d54d8d9ce32a3cceab4218ed2f6b7d35617cafe9adf84e43919cb\"\ndependencies = [\n \"libc\",\n]\n\n[[package]]\nname = \"maybe-uninit\"\nversion = \"2.0.0\"\nsource = \"registry+https://github.com/rust-lang/crates.io-index\"\nchecksum = \"60302e4db3a61da70c0cb7991976248362f30319e88850c487b9b95bbf059e00\"\n\n[[package]]\nname = \"memchr\"\nversion = \"2.4.0\"\nsource = \"registry+https://github.com/rust-lang/crates.io-index\"\nchecksum = \"b16bd47d9e329435e309c58469fe0791c2d0d1ba96ec0954152a5ae2b04387dc\"\n\n[[package]]\nname = \"memmap\"\nversion = \"0.5.2\"\nsource = \"registry+https://github.com/rust-lang/crates.io-index\"\nchecksum = \"46f3c7359028b31999287dae4e5047ddfe90a23b7dca2282ce759b491080c99b\"\ndependencies = [\n \"fs2\",\n \"kernel32-sys\",\n \"libc\",\n \"winapi 0.2.8\",\n]\n\n[[package]]\nname = \"memmap2\"\nversion = \"0.1.0\"\nsource = \"registry+https://github.com/rust-lang/crates.io-index\"\nchecksum = \"d9b70ca2a6103ac8b665dc150b142ef0e4e89df640c9e6cf295d189c3caebe5a\"\ndependencies = [\n \"libc\",\n]\n\n[[package]]\nname = \"memoffset\"\nversion = \"0.6.4\"\nsource = \"registry+https://github.com/rust-lang/crates.io-index\"\nchecksum = \"59accc507f1338036a0477ef61afdae33cde60840f4dfe481319ce3ad116ddf9\"\ndependencies = [\n \"autocfg\",\n]\n\n[[package]]\nname = \"minimal-lexical\"\nversion = \"0.2.1\"\nsource = \"registry+https://github.com/rust-lang/crates.io-index\"\nchecksum = \"68354c5c6bd36d73ff3feceb05efa59b6acb7626617f4962be322a825e61f79a\"\n\n[[package]]\nname = \"miniz_oxide\"\nversion = \"0.4.4\"\nsource = \"registry+https://github.com/rust-lang/crates.io-index\"\nchecksum = \"a92518e98c078586bc6c934028adcca4c92a53d6a958196de835170a01d84e4b\"\ndependencies = [\n \"adler\",\n \"autocfg\",\n]\n\n[[package]]\nname = \"mio\"\nversion = \"0.6.23\"\nsource = \"registry+https://github.com/rust-lang/crates.io-index\"\nchecksum = \"4afd66f5b91bf2a3bc13fad0e21caedac168ca4c707504e75585648ae80e4cc4\"\ndependencies = [\n \"cfg-if 0.1.10\",\n \"fuchsia-zircon\",\n \"fuchsia-zircon-sys\",\n \"iovec\",\n \"kernel32-sys\",\n \"libc\",\n \"log\",\n \"miow\",\n \"net2\",\n \"slab\",\n \"winapi 0.2.8\",\n]\n\n[[package]]\nname = \"mio-extras\"\nversion = \"2.0.6\"\nsource = \"registry+https://github.com/rust-lang/crates.io-index\"\nchecksum = \"52403fe290012ce777c4626790c8951324a2b9e3316b3143779c72b029742f19\"\ndependencies = [\n \"lazycell\",\n \"log\",\n \"mio\",\n \"slab\",\n]\n\n[[package]]\nname = \"miow\"\nversion = \"0.2.2\"\nsource = \"registry+https://github.com/rust-lang/crates.io-index\"\nchecksum = \"ebd808424166322d4a38da87083bfddd3ac4c131334ed55856112eb06d46944d\"\ndependencies = [\n \"kernel32-sys\",\n \"net2\",\n \"winapi 0.2.8\",\n \"ws2_32-sys\",\n]\n\n[[package]]\nname = \"ndk\"\nversion = \"0.2.1\"\nsource = \"registry+https://github.com/rust-lang/crates.io-index\"\nchecksum = \"5eb167c1febed0a496639034d0c76b3b74263636045db5489eee52143c246e73\"\ndependencies = [\n \"jni-sys\",\n \"ndk-sys\",\n \"num_enum\",\n \"thiserror\",\n]\n\n[[package]]\nname = \"ndk-glue\"\nversion = \"0.2.1\"\nsource = \"registry+https://github.com/rust-lang/crates.io-index\"\nchecksum = \"bdf399b8b7a39c6fb153c4ec32c72fd5fe789df24a647f229c239aa7adb15241\"\ndependencies = [\n \"lazy_static 1.4.0\",\n \"libc\",\n \"log\",\n \"ndk\",\n \"ndk-macro\",\n \"ndk-sys\",\n]\n\n[[package]]\nname = \"ndk-macro\"\nversion = \"0.2.0\"\nsource = \"registry+https://github.com/rust-lang/crates.io-index\"\nchecksum = \"05d1c6307dc424d0f65b9b06e94f88248e6305726b14729fd67a5e47b2dc481d\"\ndependencies = [\n \"darling\",\n \"proc-macro-crate\",\n \"proc-macro2 1.0.27\",\n \"quote 1.0.9\",\n \"syn 1.0.73\",\n]\n\n[[package]]\nname = \"ndk-sys\"\nversion = \"0.2.2\"\nsource = \"registry+https://github.com/rust-lang/crates.io-index\"\nchecksum = \"e1bcdd74c20ad5d95aacd60ef9ba40fdf77f767051040541df557b7a9b2a2121\"\n\n[[package]]\nname = \"net2\"\nversion = \"0.2.38\"\nsource = \"registry+https://github.com/rust-lang/crates.io-index\"\nchecksum = \"74d0df99cfcd2530b2e694f6e17e7f37b8e26bb23983ac530c0c97408837c631\"\ndependencies = [\n \"cfg-if 0.1.10\",\n \"libc\",\n \"winapi 0.3.9\",\n]\n\n[[package]]\nname = \"nix\"\nversion = \"0.18.0\"\nsource = \"registry+https://github.com/rust-lang/crates.io-index\"\nchecksum = \"83450fe6a6142ddd95fb064b746083fc4ef1705fe81f64a64e1d4b39f54a1055\"\ndependencies = [\n \"bitflags\",\n \"cc\",\n \"cfg-if 0.1.10\",\n \"libc\",\n]\n\n[[package]]\nname = \"nix\"\nversion = \"0.20.2\"\nsource = \"registry+https://github.com/rust-lang/crates.io-index\"\nchecksum = \"f5e06129fb611568ef4e868c14b326274959aa70ff7776e9d55323531c374945\"\ndependencies = [\n \"bitflags\",\n \"cc\",\n \"cfg-if 1.0.0\",\n \"libc\",\n \"memoffset\",\n]\n\n[[package]]\nname = \"nom\"\nversion = \"7.1.1\"\nsource = \"registry+https://github.com/rust-lang/crates.io-index\"\nchecksum = \"a8903e5a29a317527874d0402f867152a3d21c908bb0b933e416c65e301d4c36\"\ndependencies = [\n \"memchr\",\n \"minimal-lexical\",\n]\n\n[[package]]\nname = \"num-derive\"\nversion = \"0.2.5\"\nsource = \"registry+https://github.com/rust-lang/crates.io-index\"\nchecksum = \"eafd0b45c5537c3ba526f79d3e75120036502bebacbb3f3220914067ce39dbf2\"\ndependencies = [\n \"proc-macro2 0.4.30\",\n \"quote 0.6.13\",\n \"syn 0.15.44\",\n]\n\n[[package]]\nname = \"num-integer\"\nversion = \"0.1.44\"\nsource = \"registry+https://github.com/rust-lang/crates.io-index\"\nchecksum = \"d2cc698a63b549a70bc047073d2949cce27cd1c7b0a4a862d08a8031bc2801db\"\ndependencies = [\n \"autocfg\",\n \"num-traits\",\n]\n\n[[package]]\nname = \"num-iter\"\nversion = \"0.1.42\"\nsource = \"registry+https://github.com/rust-lang/crates.io-index\"\nchecksum = \"b2021c8337a54d21aca0d59a92577a029af9431cb59b909b03252b9c164fad59\"\ndependencies = [\n \"autocfg\",\n \"num-integer\",\n \"num-traits\",\n]\n\n[[package]]\nname = \"num-rational\"\nversion = \"0.2.4\"\nsource = \"registry+https://github.com/rust-lang/crates.io-index\"\nchecksum = \"5c000134b5dbf44adc5cb772486d335293351644b801551abe8f75c84cfa4aef\"\ndependencies = [\n \"autocfg\",\n \"num-integer\",\n \"num-traits\",\n]\n\n[[package]]\nname = \"num-traits\"\nversion = \"0.2.14\"\nsource = \"registry+https://github.com/rust-lang/crates.io-index\"\nchecksum = \"9a64b1ec5cda2586e284722486d802acf1f7dbdc623e2bfc57e65ca1cd099290\"\ndependencies = [\n \"autocfg\",\n]\n\n[[package]]\nname = \"num_cpus\"\nversion = \"1.13.0\"\nsource = \"registry+https://github.com/rust-lang/crates.io-index\"\nchecksum = \"05499f3756671c15885fee9034446956fff3f243d6077b91e5767df161f766b3\"\ndependencies = [\n \"hermit-abi\",\n \"libc\",\n]\n\n[[package]]\nname = \"num_enum\"\nversion = \"0.4.3\"\nsource = \"registry+https://github.com/rust-lang/crates.io-index\"\nchecksum = \"ca565a7df06f3d4b485494f25ba05da1435950f4dc263440eda7a6fa9b8e36e4\"\ndependencies = [\n \"derivative 2.2.0\",\n \"num_enum_derive\",\n]\n\n[[package]]\nname = \"num_enum_derive\"\nversion = \"0.4.3\"\nsource = \"registry+https://github.com/rust-lang/crates.io-index\"\nchecksum = \"ffa5a33ddddfee04c0283a7653987d634e880347e96b5b2ed64de07efb59db9d\"\ndependencies = [\n \"proc-macro-crate\",\n \"proc-macro2 1.0.27\",\n \"quote 1.0.9\",\n \"syn 1.0.73\",\n]\n\n[[package]]\nname = \"objc\"\nversion = \"0.2.7\"\nsource = \"registry+https://github.com/rust-lang/crates.io-index\"\nchecksum = \"915b1b472bc21c53464d6c8461c9d3af805ba1ef837e1cac254428f4a77177b1\"\ndependencies = [\n \"malloc_buf\",\n]\n\n[[package]]\nname = \"once_cell\"\nversion = \"1.16.0\"\nsource = \"registry+https://github.com/rust-lang/crates.io-index\"\nchecksum = \"86f0b0d4bf799edbc74508c1e8bf170ff5f41238e5f8225603ca7caaae2b7860\"\n\n[[package]]\nname = \"osmesa-sys\"\nversion = \"0.1.2\"\nsource = \"registry+https://github.com/rust-lang/crates.io-index\"\nchecksum = \"88cfece6e95d2e717e0872a7f53a8684712ad13822a7979bc760b9c77ec0013b\"\ndependencies = [\n \"shared_library\",\n]\n\n[[package]]\nname = \"owned_ttf_parser\"\nversion = \"0.15.2\"\nsource = \"registry+https://github.com/rust-lang/crates.io-index\"\nchecksum = \"05e6affeb1632d6ff6a23d2cd40ffed138e82f1532571a26f527c8a284bb2fbb\"\ndependencies = [\n \"ttf-parser\",\n]\n\n[[package]]\nname = \"parking_lot\"\nversion = \"0.11.2\"\nsource = \"registry+https://github.com/rust-lang/crates.io-index\"\nchecksum = \"7d17b78036a60663b797adeaee46f5c9dfebb86948d1255007a1d6be0271ff99\"\ndependencies = [\n \"instant\",\n \"lock_api\",\n \"parking_lot_core\",\n]\n\n[[package]]\nname = \"parking_lot_core\"\nversion = \"0.8.5\"\nsource = \"registry+https://github.com/rust-lang/crates.io-index\"\nchecksum = \"d76e8e1493bcac0d2766c42737f34458f1c8c50c0d23bcb24ea953affb273216\"\ndependencies = [\n \"cfg-if 1.0.0\",\n \"instant\",\n \"libc\",\n \"redox_syscall\",\n \"smallvec\",\n \"winapi 0.3.9\",\n]\n\n[[package]]\nname = \"percent-encoding\"\nversion = \"2.2.0\"\nsource = \"registry+https://github.com/rust-lang/crates.io-index\"\nchecksum = \"478c572c3d73181ff3c2539045f6eb99e5491218eae919370993b890cdbdd98e\"\n\n[[package]]\nname = \"piston\"\nversion = \"0.53.1\"\nsource = \"registry+https://github.com/rust-lang/crates.io-index\"\nchecksum = \"7f483bc0f9316e80f27c9f083fb20e8ae881a9799ad792cf683a059f3f58d6e6\"\ndependencies = [\n \"pistoncore-event_loop\",\n \"pistoncore-input\",\n \"pistoncore-window\",\n]\n\n[[package]]\nname = \"piston-float\"\nversion = \"1.0.0\"\nsource = \"registry+https://github.com/rust-lang/crates.io-index\"\nchecksum = \"f900be47e312e126cc71d35548e8e31edd3901b92ab82d1c4c4757e6b5526564\"\n\n[[package]]\nname = \"piston-gfx_texture\"\nversion = \"0.35.0\"\nsource = \"registry+https://github.com/rust-lang/crates.io-index\"\nchecksum = \"c6307afabc7fd1bdaa02c4989d0934d32187f99a0ceb28321dcb869d5c232066\"\ndependencies = [\n \"gfx\",\n \"gfx_core\",\n \"image\",\n \"piston-texture\",\n]\n\n[[package]]\nname = \"piston-graphics_api_version\"\nversion = \"1.0.1\"\nsource = \"registry+https://github.com/rust-lang/crates.io-index\"\nchecksum = \"3b06401e3ea38467d8d85b394557408107e3e56d827f0d00c9b47e902cbd1bed\"\n\n[[package]]\nname = \"piston-texture\"\nversion = \"0.6.0\"\nsource = \"registry+https://github.com/rust-lang/crates.io-index\"\nchecksum = \"3649b5f9d1ba48d95207976118e9e2ed473c1de36f6f79cc1b7ed5b75b655b61\"\n\n[[package]]\nname = \"piston-viewport\"\nversion = \"1.0.2\"\nsource = \"registry+https://github.com/rust-lang/crates.io-index\"\nchecksum = \"61ecaf8ae0d71dd9cdbbd8662b47659621c09430ff3cb880d154858d3b8ac001\"\ndependencies = [\n \"piston-float\",\n]\n\n[[package]]\nname = \"piston3d-cam\"\nversion = \"0.4.0\"\nsource = \"registry+https://github.com/rust-lang/crates.io-index\"\nchecksum = \"c29bb5a44b7cf1b86c133c3dfa734e81f1cfb1347e4ad7d48b611f28d7b75120\"\ndependencies = [\n \"quaternion\",\n \"vecmath\",\n]\n\n[[package]]\nname = \"piston3d-gfx_voxel\"\nversion = \"0.27.0\"\nsource = \"registry+https://github.com/rust-lang/crates.io-index\"\nchecksum = \"dd9a00eba4f9679bf317e102c4ecbd7712c3e21a036d7a7e57bf145754a9a615\"\ndependencies = [\n \"array\",\n \"gfx\",\n \"image\",\n \"piston-gfx_texture\",\n]\n\n[[package]]\nname = \"pistoncore-event_loop\"\nversion = \"0.53.1\"\nsource = \"registry+https://github.com/rust-lang/crates.io-index\"\nchecksum = \"41d86b3bf012430bb23694348615e37769aca0e9910539ce93674006aeeb77e6\"\ndependencies = [\n \"pistoncore-input\",\n \"pistoncore-window\",\n \"spin_sleep\",\n]\n\n[[package]]\nname = \"pistoncore-glutin_window\"\nversion = \"0.70.1\"\nsource = \"registry+https://github.com/rust-lang/crates.io-index\"\nchecksum = \"a2625037feaa575206054a7a10b397739c6c10e81be0ae65858182d6dd906d30\"\ndependencies = [\n \"gl\",\n \"glutin\",\n \"pistoncore-input\",\n \"pistoncore-window\",\n \"shader_version\",\n]\n\n[[package]]\nname = \"pistoncore-input\"\nversion = \"1.0.1\"\nsource = \"registry+https://github.com/rust-lang/crates.io-index\"\nchecksum = \"2977fed6eb16c554fd445a09a50c8a0c250f4c50f752be46a7bd9dcc5ba471f0\"\ndependencies = [\n \"bitflags\",\n \"piston-viewport\",\n \"serde\",\n \"serde_derive\",\n]\n\n[[package]]\nname = \"pistoncore-window\"\nversion = \"0.47.1\"\nsource = \"registry+https://github.com/rust-lang/crates.io-index\"\nchecksum = \"d62962b4e9cfc13143c77e032302fedc58a8f0f570d30006cdb38ba00a5e50bf\"\ndependencies = [\n \"piston-graphics_api_version\",\n \"pistoncore-input\",\n]\n\n[[package]]\nname = \"pkg-config\"\nversion = \"0.3.19\"\nsource = \"registry+https://github.com/rust-lang/crates.io-index\"\nchecksum = \"3831453b3449ceb48b6d9c7ad7c96d5ea673e9b470a1dc578c2ce6521230884c\"\n\n[[package]]\nname = \"png\"\nversion = \"0.14.1\"\nsource = \"registry+https://github.com/rust-lang/crates.io-index\"\nchecksum = \"63daf481fdd0defa2d1d2be15c674fbfa1b0fd71882c303a91f9a79b3252c359\"\ndependencies = [\n \"bitflags\",\n \"deflate\",\n \"inflate\",\n \"num-iter\",\n]\n\n[[package]]\nname = \"proc-macro-crate\"\nversion = \"0.1.5\"\nsource = \"registry+https://github.com/rust-lang/crates.io-index\"\nchecksum = \"1d6ea3c4595b96363c13943497db34af4460fb474a95c43f4446ad341b8c9785\"\ndependencies = [\n \"toml\",\n]\n\n[[package]]\nname = \"proc-macro2\"\nversion = \"0.4.30\"\nsource = \"registry+https://github.com/rust-lang/crates.io-index\"\nchecksum = \"cf3d2011ab5c909338f7887f4fc896d35932e29146c12c8d01da6b22a80ba759\"\ndependencies = [\n \"unicode-xid 0.1.0\",\n]\n\n[[package]]\nname = \"proc-macro2\"\nversion = \"1.0.27\"\nsource = \"registry+https://github.com/rust-lang/crates.io-index\"\nchecksum = \"f0d8caf72986c1a598726adc988bb5984792ef84f5ee5aa50209145ee8077038\"\ndependencies = [\n \"unicode-xid 0.2.2\",\n]\n\n[[package]]\nname = \"quaternion\"\nversion = \"0.4.1\"\nsource = \"registry+https://github.com/rust-lang/crates.io-index\"\nchecksum = \"098443236d1445368525aa1874295cb9d9fc7699b52907c78692f0b18bd8c216\"\ndependencies = [\n \"vecmath\",\n]\n\n[[package]]\nname = \"quote\"\nversion = \"0.6.13\"\nsource = \"registry+https://github.com/rust-lang/crates.io-index\"\nchecksum = \"6ce23b6b870e8f94f81fb0a363d65d86675884b34a09043c81e5562f11c1f8e1\"\ndependencies = [\n \"proc-macro2 0.4.30\",\n]\n\n[[package]]\nname = \"quote\"\nversion = \"1.0.9\"\nsource = \"registry+https://github.com/rust-lang/crates.io-index\"\nchecksum = \"c3d0b9745dc2debf507c8422de05d7226cc1f0644216dfdfead988f9b1ab32a7\"\ndependencies = [\n \"proc-macro2 1.0.27\",\n]\n\n[[package]]\nname = \"raw-window-handle\"\nversion = \"0.3.4\"\nsource = \"registry+https://github.com/rust-lang/crates.io-index\"\nchecksum = \"e28f55143d0548dad60bb4fbdc835a3d7ac6acc3324506450c5fdd6e42903a76\"\ndependencies = [\n \"libc\",\n \"raw-window-handle 0.4.3\",\n]\n\n[[package]]\nname = \"raw-window-handle\"\nversion = \"0.4.3\"\nsource = \"registry+https://github.com/rust-lang/crates.io-index\"\nchecksum = \"b800beb9b6e7d2df1fe337c9e3d04e3af22a124460fb4c30fcc22c9117cefb41\"\ndependencies = [\n \"cty\",\n]\n\n[[package]]\nname = \"rayon\"\nversion = \"1.5.1\"\nsource = \"registry+https://github.com/rust-lang/crates.io-index\"\nchecksum = \"c06aca804d41dbc8ba42dfd964f0d01334eceb64314b9ecf7c5fad5188a06d90\"\ndependencies = [\n \"autocfg\",\n \"crossbeam-deque\",\n \"either\",\n \"rayon-core\",\n]\n\n[[package]]\nname = \"rayon-core\"\nversion = \"1.9.1\"\nsource = \"registry+https://github.com/rust-lang/crates.io-index\"\nchecksum = \"d78120e2c850279833f1dd3582f730c4ab53ed95aeaaaa862a2a5c71b1656d8e\"\ndependencies = [\n \"crossbeam-channel\",\n \"crossbeam-deque\",\n \"crossbeam-utils\",\n \"lazy_static 1.4.0\",\n \"num_cpus\",\n]\n\n[[package]]\nname = \"redox_syscall\"\nversion = \"0.2.16\"\nsource = \"registry+https://github.com/rust-lang/crates.io-index\"\nchecksum = \"fb5a58c1855b4b6819d59012155603f0b22ad30cad752600aadfcb695265519a\"\ndependencies = [\n \"bitflags\",\n]\n\n[[package]]\nname = \"regex\"\nversion = \"0.2.11\"\nsource = \"registry+https://github.com/rust-lang/crates.io-index\"\nchecksum = \"9329abc99e39129fcceabd24cf5d85b4671ef7c29c50e972bc5afe32438ec384\"\ndependencies = [\n \"aho-corasick\",\n \"memchr\",\n \"regex-syntax\",\n \"thread_local\",\n \"utf8-ranges\",\n]\n\n[[package]]\nname = \"regex-syntax\"\nversion = \"0.5.6\"\nsource = \"registry+https://github.com/rust-lang/crates.io-index\"\nchecksum = \"7d707a4fa2637f2dca2ef9fd02225ec7661fe01a53623c1e6515b6916511f7a7\"\ndependencies = [\n \"ucd-util\",\n]\n\n[[package]]\nname = \"rustc-serialize\"\nversion = \"0.3.24\"\nsource = \"registry+https://github.com/rust-lang/crates.io-index\"\nchecksum = \"dcf128d1287d2ea9d80910b5f1120d0b8eede3fbf1abe91c40d39ea7d51e6fda\"\n\n[[package]]\nname = \"rusttype\"\nversion = \"0.9.3\"\nsource = \"registry+https://github.com/rust-lang/crates.io-index\"\nchecksum = \"3ff8374aa04134254b7995b63ad3dc41c7f7236f69528b28553da7d72efaa967\"\ndependencies = [\n \"ab_glyph_rasterizer\",\n \"owned_ttf_parser\",\n]\n\n[[package]]\nname = \"same-file\"\nversion = \"1.0.6\"\nsource = \"registry+https://github.com/rust-lang/crates.io-index\"\nchecksum = \"93fc1dc3aaa9bfed95e02e6eadabb4baf7e3078b0bd1b4d7b6b0b68378900502\"\ndependencies = [\n \"winapi-util\",\n]\n\n[[package]]\nname = \"scoped-tls\"\nversion = \"1.0.1\"\nsource = \"registry+https://github.com/rust-lang/crates.io-index\"\nchecksum = \"e1cf6437eb19a8f4a6cc0f7dca544973b0b78843adbfeb3683d1a94a0024a294\"\n\n[[package]]\nname = \"scoped_threadpool\"\nversion = \"0.1.9\"\nsource = \"registry+https://github.com/rust-lang/crates.io-index\"\nchecksum = \"1d51f5df5af43ab3f1360b429fa5e0152ac5ce8c0bd6485cae490332e96846a8\"\n\n[[package]]\nname = \"scopeguard\"\nversion = \"1.1.0\"\nsource = \"registry+https://github.com/rust-lang/crates.io-index\"\nchecksum = \"d29ab0c6d3fc0ee92fe66e2d99f700eab17a8d57d1c1d3b748380fb20baa78cd\"\n\n[[package]]\nname = \"serde\"\nversion = \"1.0.126\"\nsource = \"registry+https://github.com/rust-lang/crates.io-index\"\nchecksum = \"ec7505abeacaec74ae4778d9d9328fe5a5d04253220a85c4ee022239fc996d03\"\n\n[[package]]\nname = \"serde_derive\"\nversion = \"1.0.126\"\nsource = \"registry+https://github.com/rust-lang/crates.io-index\"\nchecksum = \"963a7dbc9895aeac7ac90e74f34a5d5261828f79df35cbed41e10189d3804d43\"\ndependencies = [\n \"proc-macro2 1.0.27\",\n \"quote 1.0.9\",\n \"syn 1.0.73\",\n]\n\n[[package]]\nname = \"shader_version\"\nversion = \"0.7.0\"\nsource = \"registry+https://github.com/rust-lang/crates.io-index\"\nchecksum = \"dfadbf7574784ee97f062ace17e1008fb5e7f46dd714b7dd46baf6efebd30e26\"\ndependencies = [\n \"piston-graphics_api_version\",\n]\n\n[[package]]\nname = \"shared_library\"\nversion = \"0.1.9\"\nsource = \"registry+https://github.com/rust-lang/crates.io-index\"\nchecksum = \"5a9e7e0f2bfae24d8a5b5a66c5b257a83c7412304311512a0c054cd5e619da11\"\ndependencies = [\n \"lazy_static 1.4.0\",\n \"libc\",\n]\n\n[[package]]\nname = \"slab\"\nversion = \"0.4.7\"\nsource = \"registry+https://github.com/rust-lang/crates.io-index\"\nchecksum = \"4614a76b2a8be0058caa9dbbaf66d988527d86d003c11a94fbd335d7661edcef\"\ndependencies = [\n \"autocfg\",\n]\n\n[[package]]\nname = \"smallvec\"\nversion = \"1.10.0\"\nsource = \"registry+https://github.com/rust-lang/crates.io-index\"\nchecksum = \"a507befe795404456341dfab10cef66ead4c041f62b8b11bbb92bffe5d0953e0\"\n\n[[package]]\nname = \"smithay-client-toolkit\"\nversion = \"0.12.3\"\nsource = \"registry+https://github.com/rust-lang/crates.io-index\"\nchecksum = \"4750c76fd5d3ac95fa3ed80fe667d6a3d8590a960e5b575b98eea93339a80b80\"\ndependencies = [\n \"andrew\",\n \"bitflags\",\n \"calloop\",\n \"dlib 0.4.2\",\n \"lazy_static 1.4.0\",\n \"log\",\n \"memmap2\",\n \"nix 0.18.0\",\n \"wayland-client\",\n \"wayland-cursor\",\n \"wayland-protocols\",\n]\n\n[[package]]\nname = \"spin_sleep\"\nversion = \"1.1.1\"\nsource = \"registry+https://github.com/rust-lang/crates.io-index\"\nchecksum = \"cafa7900db085f4354dbc7025e25d7a839a14360ea13b5fc4fd717f2d3b23134\"\ndependencies = [\n \"once_cell\",\n \"winapi 0.3.9\",\n]\n\n[[package]]\nname = \"strsim\"\nversion = \"0.6.0\"\nsource = \"registry+https://github.com/rust-lang/crates.io-index\"\nchecksum = \"b4d15c810519a91cf877e7e36e63fe068815c678181439f2f29e2562147c3694\"\n\n[[package]]\nname = \"strsim\"\nversion = \"0.9.3\"\nsource = \"registry+https://github.com/rust-lang/crates.io-index\"\nchecksum = \"6446ced80d6c486436db5c078dde11a9f73d42b57fb273121e160b84f63d894c\"\n\n[[package]]\nname = \"syn\"\nversion = \"0.15.44\"\nsource = \"registry+https://github.com/rust-lang/crates.io-index\"\nchecksum = \"9ca4b3b69a77cbe1ffc9e198781b7acb0c7365a883670e8f1c1bc66fba79a5c5\"\ndependencies = [\n \"proc-macro2 0.4.30\",\n \"quote 0.6.13\",\n \"unicode-xid 0.1.0\",\n]\n\n[[package]]\nname = \"syn\"\nversion = \"1.0.73\"\nsource = \"registry+https://github.com/rust-lang/crates.io-index\"\nchecksum = \"f71489ff30030d2ae598524f61326b902466f72a0fb1a8564c001cc63425bcc7\"\ndependencies = [\n \"proc-macro2 1.0.27\",\n \"quote 1.0.9\",\n \"unicode-xid 0.2.2\",\n]\n\n[[package]]\nname = \"thiserror\"\nversion = \"1.0.26\"\nsource = \"registry+https://github.com/rust-lang/crates.io-index\"\nchecksum = \"93119e4feac1cbe6c798c34d3a53ea0026b0b1de6a120deef895137c0529bfe2\"\ndependencies = [\n \"thiserror-impl\",\n]\n\n[[package]]\nname = \"thiserror-impl\"\nversion = \"1.0.26\"\nsource = \"registry+https://github.com/rust-lang/crates.io-index\"\nchecksum = \"060d69a0afe7796bf42e9e2ff91f5ee691fb15c53d38b4b62a9a53eb23164745\"\ndependencies = [\n \"proc-macro2 1.0.27\",\n \"quote 1.0.9\",\n \"syn 1.0.73\",\n]\n\n[[package]]\nname = \"thread_local\"\nversion = \"0.3.6\"\nsource = \"registry+https://github.com/rust-lang/crates.io-index\"\nchecksum = \"c6b53e329000edc2b34dbe8545fd20e55a333362d0a321909685a19bd28c3f1b\"\ndependencies = [\n \"lazy_static 1.4.0\",\n]\n\n[[package]]\nname = \"tiff\"\nversion = \"0.2.2\"\nsource = \"registry+https://github.com/rust-lang/crates.io-index\"\nchecksum = \"1e4834f28a0330cb9f3f2c87d2649dca723cb33802e2bdcf18da32759fbec7ce\"\ndependencies = [\n \"byteorder\",\n \"lzw\",\n \"num-derive\",\n \"num-traits\",\n]\n\n[[package]]\nname = \"time\"\nversion = \"0.1.44\"\nsource = \"registry+https://github.com/rust-lang/crates.io-index\"\nchecksum = \"6db9e6914ab8b1ae1c260a4ae7a49b6c5611b40328a735b21862567685e73255\"\ndependencies = [\n \"libc\",\n \"wasi\",\n \"winapi 0.3.9\",\n]\n\n[[package]]\nname = \"toml\"\nversion = \"0.5.9\"\nsource = \"registry+https://github.com/rust-lang/crates.io-index\"\nchecksum = \"8d82e1a7758622a465f8cee077614c73484dac5b836c02ff6a40d5d1010324d7\"\ndependencies = [\n \"serde\",\n]\n\n[[package]]\nname = \"ttf-parser\"\nversion = \"0.15.2\"\nsource = \"registry+https://github.com/rust-lang/crates.io-index\"\nchecksum = \"7b3e06c9b9d80ed6b745c7159c40b311ad2916abb34a49e9be2653b90db0d8dd\"\n\n[[package]]\nname = \"ucd-util\"\nversion = \"0.1.8\"\nsource = \"registry+https://github.com/rust-lang/crates.io-index\"\nchecksum = \"c85f514e095d348c279b1e5cd76795082cf15bd59b93207832abe0b1d8fed236\"\n\n[[package]]\nname = \"unicode-xid\"\nversion = \"0.1.0\"\nsource = \"registry+https://github.com/rust-lang/crates.io-index\"\nchecksum = \"fc72304796d0818e357ead4e000d19c9c174ab23dc11093ac919054d20a6a7fc\"\n\n[[package]]\nname = \"unicode-xid\"\nversion = \"0.2.2\"\nsource = \"registry+https://github.com/rust-lang/crates.io-index\"\nchecksum = \"8ccb82d61f80a663efe1f787a51b16b5a51e3314d6ac365b08639f52387b33f3\"\n\n[[package]]\nname = \"utf8-ranges\"\nversion = \"1.0.4\"\nsource = \"registry+https://github.com/rust-lang/crates.io-index\"\nchecksum = \"b4ae116fef2b7fea257ed6440d3cfcff7f190865f170cdad00bb6465bf18ecba\"\n\n[[package]]\nname = \"vecmath\"\nversion = \"1.0.0\"\nsource = \"registry+https://github.com/rust-lang/crates.io-index\"\nchecksum = \"956ae1e0d85bca567dee1dcf87fb1ca2e792792f66f87dced8381f99cd91156a\"\ndependencies = [\n \"piston-float\",\n]\n\n[[package]]\nname = \"walkdir\"\nversion = \"2.3.2\"\nsource = \"registry+https://github.com/rust-lang/crates.io-index\"\nchecksum = \"808cf2735cd4b6866113f648b791c6adc5714537bc222d9347bb203386ffda56\"\ndependencies = [\n \"same-file\",\n \"winapi 0.3.9\",\n \"winapi-util\",\n]\n\n[[package]]\nname = \"wasi\"\nversion = \"0.10.0+wasi-snapshot-preview1\"\nsource = \"registry+https://github.com/rust-lang/crates.io-index\"\nchecksum = \"1a143597ca7c7793eff794def352d41792a93c481eb1042423ff7ff72ba2c31f\"\n\n[[package]]\nname = \"wayland-client\"\nversion = \"0.28.6\"\nsource = \"registry+https://github.com/rust-lang/crates.io-index\"\nchecksum = \"e3ab332350e502f159382201394a78e3cc12d0f04db863429260164ea40e0355\"\ndependencies = [\n \"bitflags\",\n \"downcast-rs\",\n \"libc\",\n \"nix 0.20.2\",\n \"scoped-tls\",\n \"wayland-commons\",\n \"wayland-scanner\",\n \"wayland-sys\",\n]\n\n[[package]]\nname = \"wayland-commons\"\nversion = \"0.28.6\"\nsource = \"registry+https://github.com/rust-lang/crates.io-index\"\nchecksum = \"a21817947c7011bbd0a27e11b17b337bfd022e8544b071a2641232047966fbda\"\ndependencies = [\n \"nix 0.20.2\",\n \"once_cell\",\n \"smallvec\",\n \"wayland-sys\",\n]\n\n[[package]]\nname = \"wayland-cursor\"\nversion = \"0.28.6\"\nsource = \"registry+https://github.com/rust-lang/crates.io-index\"\nchecksum = \"be610084edd1586d45e7bdd275fe345c7c1873598caa464c4fb835dee70fa65a\"\ndependencies = [\n \"nix 0.20.2\",\n \"wayland-client\",\n \"xcursor\",\n]\n\n[[package]]\nname = \"wayland-egl\"\nversion = \"0.28.6\"\nsource = \"registry+https://github.com/rust-lang/crates.io-index\"\nchecksum = \"99ba1ab1e18756b23982d36f08856d521d7df45015f404a2d7c4f0b2d2f66956\"\ndependencies = [\n \"wayland-client\",\n \"wayland-sys\",\n]\n\n[[package]]\nname = \"wayland-protocols\"\nversion = \"0.28.6\"\nsource = \"registry+https://github.com/rust-lang/crates.io-index\"\nchecksum = \"286620ea4d803bacf61fa087a4242ee316693099ee5a140796aaba02b29f861f\"\ndependencies = [\n \"bitflags\",\n \"wayland-client\",\n \"wayland-commons\",\n \"wayland-scanner\",\n]\n\n[[package]]\nname = \"wayland-scanner\"\nversion = \"0.28.6\"\nsource = \"registry+https://github.com/rust-lang/crates.io-index\"\nchecksum = \"ce923eb2deb61de332d1f356ec7b6bf37094dc5573952e1c8936db03b54c03f1\"\ndependencies = [\n \"proc-macro2 1.0.27\",\n \"quote 1.0.9\",\n \"xml-rs 0.8.3\",\n]\n\n[[package]]\nname = \"wayland-sys\"\nversion = \"0.28.6\"\nsource = \"registry+https://github.com/rust-lang/crates.io-index\"\nchecksum = \"d841fca9aed7febf9bed2e9796c49bf58d4152ceda8ac949ebe00868d8f0feb8\"\ndependencies = [\n \"dlib 0.5.0\",\n \"lazy_static 1.4.0\",\n \"pkg-config\",\n]\n\n[[package]]\nname = \"winapi\"\nversion = \"0.2.8\"\nsource = \"registry+https://github.com/rust-lang/crates.io-index\"\nchecksum = \"167dc9d6949a9b857f3451275e911c3f44255842c1f7a76f33c55103a909087a\"\n\n[[package]]\nname = \"winapi\"\nversion = \"0.3.9\"\nsource = \"registry+https://github.com/rust-lang/crates.io-index\"\nchecksum = \"5c839a674fcd7a98952e593242ea400abe93992746761e38641405d28b00f419\"\ndependencies = [\n \"winapi-i686-pc-windows-gnu\",\n \"winapi-x86_64-pc-windows-gnu\",\n]\n\n[[package]]\nname = \"winapi-build\"\nversion = \"0.1.1\"\nsource = \"registry+https://github.com/rust-lang/crates.io-index\"\nchecksum = \"2d315eee3b34aca4797b2da6b13ed88266e6d612562a0c46390af8299fc699bc\"\n\n[[package]]\nname = \"winapi-i686-pc-windows-gnu\"\nversion = \"0.4.0\"\nsource = \"registry+https://github.com/rust-lang/crates.io-index\"\nchecksum = \"ac3b87c63620426dd9b991e5ce0329eff545bccbbb34f3be09ff6fb6ab51b7b6\"\n\n[[package]]\nname = \"winapi-util\"\nversion = \"0.1.5\"\nsource = \"registry+https://github.com/rust-lang/crates.io-index\"\nchecksum = \"70ec6ce85bb158151cae5e5c87f95a8e97d2c0c4b001223f33a334e3ce5de178\"\ndependencies = [\n \"winapi 0.3.9\",\n]\n\n[[package]]\nname = \"winapi-x86_64-pc-windows-gnu\"\nversion = \"0.4.0\"\nsource = \"registry+https://github.com/rust-lang/crates.io-index\"\nchecksum = \"712e227841d057c1ee1cd2fb22fa7e5a5461ae8e48fa2ca79ec42cfc1931183f\"\n\n[[package]]\nname = \"winit\"\nversion = \"0.24.0\"\nsource = \"registry+https://github.com/rust-lang/crates.io-index\"\nchecksum = \"da4eda6fce0eb84bd0a33e3c8794eb902e1033d0a1d5a31bc4f19b1b4bbff597\"\ndependencies = [\n \"bitflags\",\n \"cocoa 0.24.1\",\n \"core-foundation 0.9.3\",\n \"core-graphics 0.22.3\",\n \"core-video-sys\",\n \"dispatch\",\n \"instant\",\n \"lazy_static 1.4.0\",\n \"libc\",\n \"log\",\n \"mio\",\n \"mio-extras\",\n \"ndk\",\n \"ndk-glue\",\n \"ndk-sys\",\n \"objc\",\n \"parking_lot\",\n \"percent-encoding\",\n \"raw-window-handle 0.3.4\",\n \"smithay-client-toolkit\",\n \"wayland-client\",\n \"winapi 0.3.9\",\n \"x11-dl\",\n]\n\n[[package]]\nname = \"ws2_32-sys\"\nversion = \"0.2.1\"\nsource = \"registry+https://github.com/rust-lang/crates.io-index\"\nchecksum = \"d59cefebd0c892fa2dd6de581e937301d8552cb44489cdff035c6187cb63fa5e\"\ndependencies = [\n \"winapi 0.2.8\",\n \"winapi-build\",\n]\n\n[[package]]\nname = \"x11-dl\"\nversion = \"2.18.5\"\nsource = \"registry+https://github.com/rust-lang/crates.io-index\"\nchecksum = \"2bf981e3a5b3301209754218f962052d4d9ee97e478f4d26d4a6eced34c1fef8\"\ndependencies = [\n \"lazy_static 1.4.0\",\n \"libc\",\n \"maybe-uninit\",\n \"pkg-config\",\n]\n\n[[package]]\nname = \"xcursor\"\nversion = \"0.3.4\"\nsource = \"registry+https://github.com/rust-lang/crates.io-index\"\nchecksum = \"463705a63313cd4301184381c5e8042f0a7e9b4bb63653f216311d4ae74690b7\"\ndependencies = [\n \"nom\",\n]\n\n[[package]]\nname = \"xdg\"\nversion = \"2.2.0\"\nsource = \"registry+https://github.com/rust-lang/crates.io-index\"\nchecksum = \"d089681aa106a86fade1b0128fb5daf07d5867a509ab036d99988dec80429a57\"\n\n[[package]]\nname = \"xml-rs\"\nversion = \"0.7.0\"\nsource = \"registry+https://github.com/rust-lang/crates.io-index\"\nchecksum = \"3c1cb601d29fe2c2ac60a2b2e5e293994d87a1f6fa9687a31a15270f909be9c2\"\ndependencies = [\n \"bitflags\",\n]\n\n[[package]]\nname = \"xml-rs\"\nversion = \"0.8.3\"\nsource = \"registry+https://github.com/rust-lang/crates.io-index\"\nchecksum = \"b07db065a5cf61a7e4ba64f29e67db906fb1787316516c4e6e5ff0fea1efcd8a\"\n\n[[package]]\nname = \"zip\"\nversion = \"0.5.13\"\nsource = \"registry+https://github.com/rust-lang/crates.io-index\"\nchecksum = \"93ab48844d61251bb3835145c521d88aa4031d7139e8485990f60ca911fa0815\"\ndependencies = [\n \"byteorder\",\n \"bzip2\",\n \"crc32fast\",\n \"flate2\",\n \"thiserror\",\n \"time\",\n]\n"
        },
        {
          "name": "Cargo.png",
          "type": "blob",
          "size": 153.248046875,
          "content": null
        },
        {
          "name": "Cargo.toml",
          "type": "blob",
          "size": 0.78515625,
          "content": "[package]\n\nname = \"hematite\"\nversion = \"0.0.34\"\nedition = \"2018\"\nlicense = \"MIT\"\nauthors = [\"bvssvni <bvssvni@gmail.com>\"]\nkeywords = [\"minecraft\", \"piston\", \"client\"]\ndescription = \"A simple Minecraft client\"\nrepository = \"https://github.com/PistonDevelopers/hematite.git\"\nhomepage = \"http://hematite.piston.rs\"\nexclude = [\"home/*\"]\n\n[profile.release]\nopt-level = 2\ndebug = false\n\n[[bin]]\n\nname = \"hematite\"\npath = \"src/main.rs\"\n\n[dependencies]\nbyteorder = \"1.4.3\"\ncamera_controllers = \"0.32\"\ndocopt = \"0.7.0\"\nflate2 = \"1.0.20\"\nfps_counter = \"2.0.0\"\ngfx = \"0.17.1\"\ngfx_core = \"0.8.3\"\ngfx_device_gl = \"0.15.5\"\nlibc = \"0.2.97\"\nmemmap = \"0.5.2\"\npiston = \"0.53\"\npiston3d-gfx_voxel = \"0.27\"\npistoncore-glutin_window = \"0.70\"\nrustc-serialize = \"0.3.24\"\nshader_version = \"0.7\"\nvecmath = \"1.0.0\"\nzip = \"0.5.13\"\n"
        },
        {
          "name": "LICENSE",
          "type": "blob",
          "size": 1.056640625,
          "content": "The MIT License (MIT)\n\nCopyright (c) 2014 PistonDevelopers\n\nPermission is hereby granted, free of charge, to any person obtaining a copy\nof this software and associated documentation files (the \"Software\"), to deal\nin the Software without restriction, including without limitation the rights\nto use, copy, modify, merge, publish, distribute, sublicense, and/or sell\ncopies of the Software, and to permit persons to whom the Software is\nfurnished to do so, subject to the following conditions:\n\nThe above copyright notice and this permission notice shall be included in all\ncopies or substantial portions of the Software.\n\nTHE SOFTWARE IS PROVIDED \"AS IS\", WITHOUT WARRANTY OF ANY KIND, EXPRESS OR\nIMPLIED, INCLUDING BUT NOT LIMITED TO THE WARRANTIES OF MERCHANTABILITY,\nFITNESS FOR A PARTICULAR PURPOSE AND NONINFRINGEMENT. IN NO EVENT SHALL THE\nAUTHORS OR COPYRIGHT HOLDERS BE LIABLE FOR ANY CLAIM, DAMAGES OR OTHER\nLIABILITY, WHETHER IN AN ACTION OF CONTRACT, TORT OR OTHERWISE, ARISING FROM,\nOUT OF OR IN CONNECTION WITH THE SOFTWARE OR THE USE OR OTHER DEALINGS IN THE\nSOFTWARE."
        },
        {
          "name": "README.md",
          "type": "blob",
          "size": 1.0078125,
          "content": "# hematite [![Build Status](https://travis-ci.org/PistonDevelopers/hematite.svg?branch=master)](https://travis-ci.org/PistonDevelopers/hematite)\n\nA simple Minecraft written in Rust with the Piston game engine\n\n![screenshot](./screenshot.png)\n\n## How To Open a World\n\n*This method is only for personal use. Never distribute copyrighted content from Minecraft.*\n\n* In the Minecraft Launcher, click the button New Profile\n* In the drop down \"use version\", select `1.8.8`\n* Click Save Profile\n* Click Play (this will download the snapshot)\n* Quit Minecraft\n\n* **Copy** your world save to to the hematite directory (It may corrupt your world)\n* Save Locations:\n  * **Windows:** `%appdata%\\.minecraft\\saves\\`\n  * **OSX:** `~/Library/Application Support/minecraft/saves/`\n  * **Linux/Other:** `~/.minecraft/saves/`\n* Run hematite with: `cargo run --release -- -p \"./<WORLD_NAME>\"`\n\n## Dependencies\n\n![dependencies](./Cargo.png)\n\n[How to contribute](https://github.com/PistonDevelopers/piston/blob/master/CONTRIBUTING.md)\n"
        },
        {
          "name": "clippy.toml",
          "type": "blob",
          "size": 0.0390625,
          "content": "single-char-binding-names-threshold = 7\n"
        },
        {
          "name": "rustfmt.toml",
          "type": "blob",
          "size": 0.072265625,
          "content": "edition = \"2018\"\nuse_try_shorthand = true\nuse_field_init_shorthand = true\n"
        },
        {
          "name": "screenshot.png",
          "type": "blob",
          "size": 194.353515625,
          "content": null
        },
        {
          "name": "src",
          "type": "tree",
          "content": null
        }
      ]
    }
  ]
}